potatoscript/potatoConfig.py
python/CodeTemplate.py
python/codepython123.py
python/pthonTemplate.py
python/pyTemplate.py
python/pypiTemplate.py
python/pysonTemplate.py
python/pythonTemplate.py
python/xTemplate.py
codepython123-1.6.6.dist-info/METADATA
codepython123-1.6.6.dist-info/WHEEL
codepython123-1.6.6.dist-info/top_level.txt
codepython123-1.6.6.dist-info/RECORD
