Metadata-Version: 2.1
Name: codepython123
Version: 1.6.6
Summary: A simple Template for create python project
Author: ks lim
Author-email: kianseng.lim@sony.com
